leapdna/__init__.py
leapdna/blob.py
leapdna/errors.py
leapdna/map.py
leapdna/readers.py
leapdna/api/__init__.py
leapdna/blocks/__init__.py
leapdna/blocks/allele.py
leapdna/blocks/base.py
leapdna/blocks/locus.py
leapdna/blocks/observation.py
leapdna/data/map.json
tests/__init__.py
tests/support.py
tests/test_allele.py
tests/test_base_block.py
tests/test_blob.py
tests/test_loading.py
tests/test_locus.py
tests/test_map.py
tests/test_observation_block.py
leapdna-0.1.0.dist-info/LICENSE
leapdna-0.1.0.dist-info/METADATA
leapdna-0.1.0.dist-info/WHEEL
leapdna-0.1.0.dist-info/top_level.txt
leapdna-0.1.0.dist-info/RECORD
