Metadata-Version: 2.1
Name: leapdna
Version: 0.1.0
Summary: A Python 3.9 implementation of the leapdna toolkit
Home-page: https://github.com/knifecake/leapdna-python
Author: Elias Hernandis
Author-email: elias@hernandis.me
License: UNKNOWN
Platform: UNKNOWN
Classifier: Programming Language :: Python :: 3
Classifier: License :: OSI Approved :: MIT License
Classifier: Operating System :: OS Independent
Requires-Python: >=3.9
